distance.py
hnsw.py
node.py
search.py
hnsw_lite-0.1.3.dist-info/licenses/LICENSE
test/__init__.py
test/test_distance.py
test/test_hnsw.py
test/test_node.py
test/test_search.py
hnsw_lite-0.1.3.dist-info/METADATA
hnsw_lite-0.1.3.dist-info/WHEEL
hnsw_lite-0.1.3.dist-info/top_level.txt
hnsw_lite-0.1.3.dist-info/RECORD
