Metadata-Version: 2.4
Name: hnsw-lite
Version: 0.1.3
Summary: A lightweight, pure Python implementation of HNSW algorithm
Home-page: https://github.com/chandb5/HNSW-Lite/
Author: Chand
Author-email: chandbud5@gmail.com
Project-URL: Bug Tracker, https://github.com/chandb5/HNSW-Lite/issues
Classifier: Programming Language :: Python :: 3
Classifier: License :: OSI Approved :: MIT License
Classifier: Operating System :: OS Independent
Requires-Python: >=3.10
License-File: LICENSE
Requires-Dist: numpy
Dynamic: author
Dynamic: author-email
Dynamic: classifier
Dynamic: description
Dynamic: description-content-type
Dynamic: home-page
Dynamic: license-file
Dynamic: project-url
Dynamic: requires-dist
Dynamic: requires-python
Dynamic: summary
